Metadata-Version: 2.4
Name: pyinels
Version: 0.6.16
Summary: Python library for iNels BUS
Home-page: https://github.com/JH-Soft-Technology/pyinels
Author: JH Soft Technology
Author-email: horalek.jiri@gmail.com
License: MIT
Keywords: iNels,Elko EP,Home assistant integration
Classifier: License :: OSI Approved :: MIT License
Classifier: Programming Language :: Python :: 3
Classifier: Programming Language :: Python :: 3.9
License-File: LICENSE
Dynamic: author
Dynamic: author-email
Dynamic: classifier
Dynamic: description
Dynamic: description-content-type
Dynamic: home-page
Dynamic: keywords
Dynamic: license
Dynamic: license-file
Dynamic: summary
